{
    "http://dbpedia.org/ontology/wikiPageID": [
        {
            "datatype": "http://www.w3.org/2001/XMLSchema#integer",
            "type": "literal",
            "value": 3326839
        }
    ],
    "http://dbpedia.org/ontology/wikiPageLength": [
        {
            "datatype": "http://www.w3.org/2001/XMLSchema#nonNegativeInteger",
            "type": "literal",
            "value": "1502"
        }
    ],
    "http://dbpedia.org/ontology/wikiPageOutDegree": [
        {
            "datatype": "http://www.w3.org/2001/XMLSchema#nonNegativeInteger",
            "type": "literal",
            "value": "49"
        }
    ],
    "http://dbpedia.org/ontology/wikiPageRevisionID": [
        {
            "datatype": "http://www.w3.org/2001/XMLSchema#integer",
            "type": "literal",
            "value": 59143412
        }
    ],
    "http://dbpedia.org/ontology/wikiPageWikiLink": [
        {
            "type": "uri",
            "value": "http://ja.dbpedia.org/resource/源済政"
        },
        {
            "type": "uri",
            "value": "http://ja.dbpedia.org/resource/従四位上"
        },
        {
            "type": "uri",
            "value": "http://ja.dbpedia.org/resource/公卿補任"
        },
        {
            "type": "uri",
            "value": "http://ja.dbpedia.org/resource/正四位下"
        },
        {
            "type": "uri",
            "value": "http://ja.dbpedia.org/resource/右近衛中将"
        },
        {
            "type": "uri",
            "value": "http://ja.dbpedia.org/resource/備後介"
        },
        {
            "type": "uri",
            "value": "http://ja.dbpedia.org/resource/藤原氏"
        },
        {
            "type": "uri",
            "value": "http://ja.dbpedia.org/resource/藤原能長"
        },
        {
            "type": "uri",
            "value": "http://ja.dbpedia.org/resource/藤原道子_(女御)"
        },
        {
            "type": "uri",
            "value": "http://ja.dbpedia.org/resource/侍従"
        },
        {
            "type": "uri",
            "value": "http://ja.dbpedia.org/resource/正二位"
        },
        {
            "type": "uri",
            "value": "http://ja.dbpedia.org/resource/藤原長忠"
        },
        {
            "type": "uri",
            "value": "http://ja.dbpedia.org/resource/従四位下"
        },
        {
            "type": "uri",
            "value": "http://ja.dbpedia.org/resource/日本"
        },
        {
            "type": "uri",
            "value": "http://ja.dbpedia.org/resource/正五位下"
        },
        {
            "type": "uri",
            "value": "http://ja.dbpedia.org/resource/従三位"
        },
        {
            "type": "uri",
            "value": "http://ja.dbpedia.org/resource/Category:平安時代後期の貴族"
        },
        {
            "type": "uri",
            "value": "http://ja.dbpedia.org/resource/1043年"
        },
        {
            "type": "uri",
            "value": "http://ja.dbpedia.org/resource/左近衛権中将"
        },
        {
            "type": "uri",
            "value": "http://ja.dbpedia.org/resource/伊予権守"
        },
        {
            "type": "uri",
            "value": "http://ja.dbpedia.org/resource/従五位下"
        },
        {
            "type": "uri",
            "value": "http://ja.dbpedia.org/resource/仁豪"
        },
        {
            "type": "uri",
            "value": "http://ja.dbpedia.org/resource/Category:没年不明"
        },
        {
            "type": "uri",
            "value": "http://ja.dbpedia.org/resource/御堂流"
        },
        {
            "type": "uri",
            "value": "http://ja.dbpedia.org/resource/Category:平安時代中期の貴族"
        },
        {
            "type": "uri",
            "value": "http://ja.dbpedia.org/resource/平安時代"
        },
        {
            "type": "uri",
            "value": "http://ja.dbpedia.org/resource/正三位"
        },
        {
            "type": "uri",
            "value": "http://ja.dbpedia.org/resource/藤原宗信"
        },
        {
            "type": "uri",
            "value": "http://ja.dbpedia.org/resource/藤原北家"
        },
        {
            "type": "uri",
            "value": "http://ja.dbpedia.org/resource/藤原長明"
        },
        {
            "type": "uri",
            "value": "http://ja.dbpedia.org/resource/Category:1043年生"
        },
        {
            "type": "uri",
            "value": "http://ja.dbpedia.org/resource/実兼"
        },
        {
            "type": "uri",
            "value": "http://ja.dbpedia.org/resource/右近衛権中将"
        },
        {
            "type": "uri",
            "value": "http://ja.dbpedia.org/resource/弾正尹"
        },
        {
            "type": "uri",
            "value": "http://ja.dbpedia.org/resource/Category:御堂流"
        },
        {
            "type": "uri",
            "value": "http://ja.dbpedia.org/resource/権中納言"
        },
        {
            "type": "uri",
            "value": "http://ja.dbpedia.org/resource/周防権守"
        },
        {
            "type": "uri",
            "value": "http://ja.dbpedia.org/resource/公卿"
        },
        {
            "type": "uri",
            "value": "http://ja.dbpedia.org/resource/従五位上"
        },
        {
            "type": "uri",
            "value": "http://ja.dbpedia.org/resource/蔵人頭"
        },
        {
            "type": "uri",
            "value": "http://ja.dbpedia.org/resource/右近衛少将"
        },
        {
            "type": "uri",
            "value": "http://ja.dbpedia.org/resource/長久"
        },
        {
            "type": "uri",
            "value": "http://ja.dbpedia.org/resource/参議"
        },
        {
            "type": "uri",
            "value": "http://ja.dbpedia.org/resource/近江介"
        },
        {
            "type": "uri",
            "value": "http://ja.dbpedia.org/resource/道覚"
        },
        {
            "type": "uri",
            "value": "http://ja.dbpedia.org/resource/従二位"
        }
    ],
    "http://ja.dbpedia.org/property/wikiPageUsesTemplate": [
        {
            "type": "uri",
            "value": "http://ja.dbpedia.org/resource/Template:People-stub"
        },
        {
            "type": "uri",
            "value": "http://ja.dbpedia.org/resource/Template:Japanese-history-stub"
        },
        {
            "type": "uri",
            "value": "http://ja.dbpedia.org/resource/Template:基礎情報_公家"
        }
    ],
    "http://ja.dbpedia.org/property/兄弟": [
        {
            "type": "uri",
            "value": "http://ja.dbpedia.org/resource/藤原長忠"
        },
        {
            "type": "uri",
            "value": "http://ja.dbpedia.org/resource/仁豪"
        },
        {
            "type": "uri",
            "value": "http://ja.dbpedia.org/resource/藤原宗信"
        },
        {
            "type": "uri",
            "value": "http://ja.dbpedia.org/resource/藤原長明"
        },
        {
            "type": "uri",
            "value": "http://ja.dbpedia.org/resource/藤原道子_(女御)"
        }
    ],
    "http://ja.dbpedia.org/property/子": [
        {
            "type": "uri",
            "value": "http://ja.dbpedia.org/resource/道覚"
        },
        {
            "type": "uri",
            "value": "http://ja.dbpedia.org/resource/実兼"
        }
    ],
    "http://ja.dbpedia.org/property/官位": [
        {
            "lang": "ja",
            "type": "literal",
            "value": "正二位権中納言"
        }
    ],
    "http://ja.dbpedia.org/property/時代": [
        {
            "type": "uri",
            "value": "http://ja.dbpedia.org/resource/平安時代"
        }
    ],
    "http://ja.dbpedia.org/property/死没": [
        {
            "lang": "ja",
            "type": "literal",
            "value": "不詳"
        }
    ],
    "http://ja.dbpedia.org/property/氏名": [
        {
            "lang": "ja",
            "type": "literal",
            "value": "藤原基長"
        }
    ],
    "http://ja.dbpedia.org/property/氏族": [
        {
            "type": "uri",
            "value": "http://ja.dbpedia.org/resource/御堂流"
        },
        {
            "type": "uri",
            "value": "http://ja.dbpedia.org/resource/藤原氏"
        },
        {
            "type": "uri",
            "value": "http://ja.dbpedia.org/resource/藤原北家"
        }
    ],
    "http://ja.dbpedia.org/property/父母": [
        {
            "type": "uri",
            "value": "http://ja.dbpedia.org/resource/源済政"
        },
        {
            "type": "uri",
            "value": "http://ja.dbpedia.org/resource/藤原能長"
        }
    ],
    "http://ja.dbpedia.org/property/生誕": [
        {
            "lang": "ja",
            "type": "literal",
            "value": "長久4年（1043年）"
        }
    ],
    "http://purl.org/dc/terms/subject": [
        {
            "type": "uri",
            "value": "http://ja.dbpedia.org/resource/Category:平安時代中期の貴族"
        },
        {
            "type": "uri",
            "value": "http://ja.dbpedia.org/resource/Category:御堂流"
        },
        {
            "type": "uri",
            "value": "http://ja.dbpedia.org/resource/Category:1043年生"
        },
        {
            "type": "uri",
            "value": "http://ja.dbpedia.org/resource/Category:平安時代後期の貴族"
        },
        {
            "type": "uri",
            "value": "http://ja.dbpedia.org/resource/Category:没年不明"
        }
    ],
    "http://www.w3.org/2000/01/rdf-schema#label": [
        {
            "lang": "ja",
            "type": "literal",
            "value": "藤原基長"
        }
    ],
    "http://www.w3.org/ns/prov#wasDerivedFrom": [
        {
            "type": "uri",
            "value": "http://ja.wikipedia.org/wiki/藤原基長?oldid=59143412"
        }
    ],
    "http://xmlns.com/foaf/0.1/isPrimaryTopicOf": [
        {
            "type": "uri",
            "value": "http://ja.wikipedia.org/wiki/藤原基長"
        }
    ]
}