[
  {
    "@id": "https://nakamura196.github.io/hi_person/entity/chname/三善清行.json",
    "http://schema.org/description": [
      {
        "@value": "[生]承和14(847)[没]延喜18(918).12.7. 京都平安時代中期の学者。「きよつら」とも読む。字，三耀。号，居逸。氏吉の3男。母は佐伯氏。巨勢文雄の弟子。貞観 16 (874) 年文章得業生となり，大学少允，少内記を経て仁和3 (887) 年従五位下，次いで大内記に転じ，同4年藤原佐世らと連署して阿衡の勘文を奉った (→阿衡事件 ) 。昌泰3 (900) 年刑部大輔，文章博士となり，『史記』を講述した。また辛酉革命の議を奉り，いれられて延喜と改元された。延喜1 (901) 年大学頭を兼ね，式部少輔，式部権大輔を経て同 14年式部大輔。この年醍醐天皇の詔に応じて律令制崩壊の現状を具体的に述べた意見封事 12ヵ条を奉った。同 16年善法寺を建立，翌年参議に任じられ，次いで宮内卿を兼ね，朔旦冬至 (さくたんとうじ) の賀表をつくり，また深紅の衣服の禁止を奏請した。応永 11 (1404) 年贈正二位大納言。詩，易に長じ，また明法に明るく，延喜5 (905) 年以来『延喜格式』の編集にあたった。『円珍和尚伝』 (902) ，『藤原保則伝』 (907) ，説話『善家秘記』などの著書がある。"
      },
      {
        "@value": "三善 清行（みよし の きよゆき/きよつら）は平安時代中期の公卿、漢学者。淡路守三善氏吉の三男。正義感に溢れた経世家で権威に屈せず、そのために官位が停滞したと言われている。"
      }
    ],
    "http://www.w3.org/2000/01/rdf-schema#label": [
      {
        "@value": "三善清行"
      }
    ],
    "http://www.w3.org/2002/07/owl#sameAs": [
      {
        "@id": "http://ja.wikipedia.org/wiki/三善清行"
      },
      {
        "@id": "https://kotobank.jp/word/三善清行"
      }
    ]
  }
]