[
  {
    "@id": "https://nakamura196.github.io/hi_person/entity/chname/藤原公光.json",
    "http://schema.org/description": [
      {
        "@value": "1130－1178　平安時代後期の公卿(くぎょう)。大治(だいじ)5年生まれ。保元(ほうげん)3年参議,永暦(えいりゃく)元年権(ごんの)中納言。検非違使(けびいし)別当や左衛門督(かみ)をかねた。従二位。永万2年突然官職を解かれた。「千載和歌集」以下の勅撰集に8首とられている。治承(じしょう)2年1月12日死去。49歳。"
      }
    ],
    "http://www.w3.org/2000/01/rdf-schema#label": [
      {
        "@value": "藤原公光"
      }
    ],
    "http://www.w3.org/2002/07/owl#sameAs": [
      {
        "@id": "https://kotobank.jp/word/藤原公光"
      }
    ]
  }
]